pydadjoke/__init__.py
pydadjoke/dad_jokes.py
test_github_actions_jg-0.0.14.dist-info/METADATA
test_github_actions_jg-0.0.14.dist-info/WHEEL
test_github_actions_jg-0.0.14.dist-info/top_level.txt
test_github_actions_jg-0.0.14.dist-info/RECORD
