Metadata-Version: 2.1
Name: test-github-actions-jg
Version: 0.0.14
Summary: Dad jokes in Python
Home-page: https://www.jarredglaser.com/
Author: Jarred Glaser
Author-email: jarred.glaser@gmail.com
License: MIT License
Keywords: jokes,joke,dadjokes
Platform: ALL
Classifier: Development Status :: 5 - Production/Stable
Classifier: Intended Audience :: Developers
Classifier: Programming Language :: Python :: 3.8
Classifier: License :: OSI Approved :: MIT License
Requires-Dist: pandas
